Flask_OmMongo-1.1.1.dist-info/DESCRIPTION.rst
Flask_OmMongo-1.1.1.dist-info/METADATA
Flask_OmMongo-1.1.1.dist-info/RECORD
Flask_OmMongo-1.1.1.dist-info/WHEEL
Flask_OmMongo-1.1.1.dist-info/metadata.json
Flask_OmMongo-1.1.1.dist-info/top_level.txt
flask_ommongo/__init__.py
flask_ommongo/meta.py
